COPYING.txt
HISTORY.rst
MANIFEST.in
README.rst
setup.py
ffs/__init__.py
ffs/_path_blacklists.py
ffs/_py3k.py
ffs/_unittest31.py
ffs/_version.py
ffs/exceptions.py
ffs/filesystem.py
ffs/formats.py
ffs/nix.py
ffs/nixargs.py
ffs/path.py
ffs/util.py
ffs.egg-info/PKG-INFO
ffs.egg-info/SOURCES.txt
ffs.egg-info/dependency_links.txt
ffs.egg-info/requires.txt
ffs.egg-info/top_level.txt
ffs/contrib/__init__.py
ffs/contrib/archive.py
ffs/contrib/http.py
ffs/contrib/mold.py
test/test_ffs.py
test/test_filesystem.py
test/test_formats.py
test/test_nix.py
test/test_nixargs.py
test/test_path.py
test/test_regression.py
test/test_util.py