Metadata-Version: 1.1
Name: ffs
Version: 0.0.8.2
Summary: Python Filesystem Api helpers
Home-page: http://www.deadpansincerity.com/docs/ffs
Author: David Miller
Author-email: david@deadpansincerity.com
License: UNKNOWN
Platform: UNKNOWN
Classifier: Programming Language :: Python
Classifier: Programming Language :: Python :: 2.7
Classifier: Programming Language :: Python :: 2.6
Classifier: Programming Language :: Python :: 3.1
Classifier: License :: OSI Approved :: Apache Software License
Classifier: Operating System :: OS Independent
Classifier: Development Status :: 2 - Pre-Alpha
Classifier: Intended Audience :: Developers
Classifier: Topic :: Software Development :: Libraries
